gitbrancher.py
gitbrancher-1.2.1.dist-info/entry_points.txt
gitbrancher-1.2.1.dist-info/LICENSE
gitbrancher-1.2.1.dist-info/WHEEL
gitbrancher-1.2.1.dist-info/METADATA
gitbrancher-1.2.1.dist-info/RECORD
