Metadata-Version: 2.1
Name: gitbrancher
Version: 1.2.1
Summary: Manage git workflow between multiple branches
License: MIT
Author: Ken Kinder
Author-email: ken+github@kkinder.com
Requires-Python: >=3.9,<4.0
Classifier: License :: OSI Approved :: MIT License
Classifier: Programming Language :: Python :: 3
Classifier: Programming Language :: Python :: 3.9
Classifier: Programming Language :: Python :: 3.10
Classifier: Programming Language :: Python :: 3.11
Requires-Dist: rich (>=13.7.1,<14.0.0)
